hashback/__init__.py
hashback/algorithms.py
hashback/cmdline.py
hashback/file_filter.py
hashback/http_client.py
hashback/http_protocol.py
hashback/local_database.py
hashback/local_file_system.py
hashback/log_config.py
hashback/misc.py
hashback/protocol.py
hashback/basic_auth/__init__.py
hashback/basic_auth/basic_auth.py
hashback/basic_auth/client.py
hashback/basic_auth/server.py
hashback/db_admin/__init__.py
hashback/db_admin/__main__.py
hashback/db_admin/check.py
hashback/db_admin/db_admin.py
hashback/db_admin/migrate.py
hashback/server/__init__.py
hashback/server/app.py
hashback/server/security.py
hashback-0.1a3.dist-info/LICENCE.md
hashback-0.1a3.dist-info/METADATA
hashback-0.1a3.dist-info/WHEEL
hashback-0.1a3.dist-info/entry_points.txt
hashback-0.1a3.dist-info/top_level.txt
hashback-0.1a3.dist-info/zip-safe
hashback-0.1a3.dist-info/RECORD
