Metadata-Version: 2.1
Name: hashback
Version: 0.1a3
Summary: Backup server and client which indexes files and directories by sha256sum to save space.
Home-page: https://github.com/couling/BackupServer
Author: Philip Couling
Author-email: couling@gmail.com
License: MIT
Platform: any
Classifier: License :: OSI Approved :: MIT License
Classifier: Programming Language :: Python :: 3
Classifier: Programming Language :: Python :: 3.8
License-File: LICENCE.md
Requires-Dist: pydantic
Requires-Dist: click
Requires-Dist: appdirs
Requires-Dist: python-dateutil
Requires-Dist: requests
Provides-Extra: server
Requires-Dist: python-multipart ; extra == 'server'
Requires-Dist: fastapi ; extra == 'server'
Requires-Dist: uvicorn ; extra == 'server'
Requires-Dist: asyncstdlib ; extra == 'server'
Provides-Extra: tests
Requires-Dist: fastapi ; extra == 'tests'
Requires-Dist: python-multipart ; extra == 'tests'
Requires-Dist: asyncstdlib ; extra == 'tests'
Requires-Dist: pytest ; extra == 'tests'
Requires-Dist: pytest-asyncio ; extra == 'tests'
